cfabric_benchmarks/__init__.py
cfabric_benchmarks/cli.py
cfabric_benchmarks/py.typed.py
cfabric_benchmarks/analysis/__init__.py
cfabric_benchmarks/analysis/comparison.py
cfabric_benchmarks/analysis/statistics.py
cfabric_benchmarks/corpora/__init__.py
cfabric_benchmarks/corpora/download.py
cfabric_benchmarks/corpora/validate.py
cfabric_benchmarks/generators/__init__.py
cfabric_benchmarks/generators/validator.py
cfabric_benchmarks/models/__init__.py
cfabric_benchmarks/models/config.py
cfabric_benchmarks/models/environment.py
cfabric_benchmarks/models/latency.py
cfabric_benchmarks/models/memory.py
cfabric_benchmarks/models/progressive.py
cfabric_benchmarks/models/statistics.py
cfabric_benchmarks/output/__init__.py
cfabric_benchmarks/output/csv_writer.py
cfabric_benchmarks/output/loaders.py
cfabric_benchmarks/output/metadata.py
cfabric_benchmarks/queries/__init__.py
cfabric_benchmarks/queries/curated.py
cfabric_benchmarks/runners/__init__.py
cfabric_benchmarks/runners/base.py
cfabric_benchmarks/runners/isolation.py
cfabric_benchmarks/runners/latency.py
cfabric_benchmarks/runners/memory.py
cfabric_benchmarks/runners/progressive.py
cfabric_benchmarks/visualization/__init__.py
cfabric_benchmarks/visualization/charts.py
cfabric_benchmarks/visualization/reports.py
cfabric_benchmarks-0.1.3.dist-info/METADATA
cfabric_benchmarks-0.1.3.dist-info/WHEEL
cfabric_benchmarks-0.1.3.dist-info/entry_points.txt
cfabric_benchmarks-0.1.3.dist-info/top_level.txt
cfabric_benchmarks-0.1.3.dist-info/RECORD
