Metadata-Version: 2.4
Name: cfabric-benchmarks
Version: 0.1.3
Summary: Comprehensive benchmarking suite for Context-Fabric vs Text-Fabric
Author: Cody Kingham
License: MIT
Project-URL: Homepage, https://context-fabric.ai
Project-URL: Repository, https://github.com/Context-Fabric/context-fabric
Project-URL: Issues, https://github.com/Context-Fabric/context-fabric/issues
Classifier: Development Status :: 3 - Alpha
Classifier: Intended Audience :: Science/Research
Classifier: License :: OSI Approved :: MIT License
Classifier: Programming Language :: Python :: 3.13
Requires-Python: >=3.13
Requires-Dist: context-fabric>=0.4.0
Requires-Dist: text-fabric>=12.0
Requires-Dist: pydantic>=2.0
Requires-Dist: click>=8.0
Requires-Dist: numpy>=1.26
Requires-Dist: pandas>=2.0
Requires-Dist: matplotlib>=3.8
Requires-Dist: seaborn>=0.13
Requires-Dist: psutil>=5.9
Requires-Dist: scipy>=1.11
Provides-Extra: dev
Requires-Dist: pytest>=7.0; extra == "dev"
Requires-Dist: pytest-cov; extra == "dev"
Requires-Dist: ruff; extra == "dev"
Provides-Extra: docs
Requires-Dist: griffe>=1.0; extra == "docs"
Requires-Dist: griffe-typingdoc>=0.2; extra == "docs"
